libstreamvbyte.cpython-39-i386-linux-gnu.so
libstreamvbyte.libs/libstdc++-d2a021ba.so.6.0.32
libstreamvbyte.libs/libgcc_s-f3fb5a36.so.1
libstreamvbyte-0.3.8.dist-info/WHEEL
libstreamvbyte-0.3.8.dist-info/LICENSE
libstreamvbyte-0.3.8.dist-info/top_level.txt
libstreamvbyte-0.3.8.dist-info/RECORD
libstreamvbyte-0.3.8.dist-info/METADATA
