Metadata-Version: 2.1
Name: libstreamvbyte
Version: 0.3.8
Summary: A C++ implementation of StreamVByte, with Python bindings.
Home-page: https://github.com/wst24365888/libstreamvbyte
Author: HSING-HAN WU (Xyphuz)
Author-email: xyphuzwu@gmail.com
Maintainer: HSING-HAN WU (Xyphuz)
Maintainer-email: xyphuzwu@gmail.com
License: MIT
Keywords: streamvbyte,libstreamvbyte,vbyte,integer,compression,SIMD,vectorization,SSSE3,NEON,SSE2NEON,Python,C++,CMake,pybind11
Classifier: License :: OSI Approved :: MIT License
Classifier: Operating System :: MacOS
Classifier: Operating System :: Microsoft :: Windows
Classifier: Operating System :: POSIX :: Linux
Classifier: Programming Language :: C++
Classifier: Programming Language :: Python
Classifier: Programming Language :: Python :: 3.8
Classifier: Programming Language :: Python :: 3.9
Classifier: Programming Language :: Python :: 3.10
Classifier: Programming Language :: Python :: 3.11
Classifier: Programming Language :: Python :: 3.12
Classifier: Programming Language :: Python :: 3.13
Classifier: Programming Language :: Python :: Implementation :: CPython
Classifier: Topic :: System :: Archiving :: Compression
Classifier: Topic :: Software Development :: Libraries :: Python Modules
Requires-Python: >=3.8,<4.0
License-File: LICENSE
